kleio/__init__.py
kleio/config.py
kleio/stores.py
kleio/utils/__init__.py
kleio/utils/exceptions.py
kleio/utils/util.py
kleio/utils/vc.py
kleio/utils/version.py
tests/__init__.py
tests/test_creation.py
tests/test_vcs.py
tests/test_write.py
pykleio-0.5.1.dist-info/LICENSE
pykleio-0.5.1.dist-info/METADATA
pykleio-0.5.1.dist-info/WHEEL
pykleio-0.5.1.dist-info/top_level.txt
pykleio-0.5.1.dist-info/RECORD
