Metadata-Version: 2.1
Name: pykleio
Version: 0.5.1
Summary: Versioned Storage Python SDK - enable version management for nd data
Home-page: https://github.com/JaneliaSciComp/KLEIO-Python-SDK
Author: Marwan Zouinkhi
Author-email: zouinkhi.marwan@gmail.com
Project-URL: Bug Tracker, https://github.com/JaneliaSciComp/KLEIO-Python-SDK/issues
Classifier: Programming Language :: Python :: 3
Classifier: License :: OSI Approved :: MIT License
Classifier: Operating System :: OS Independent
Requires-Python: >=3.6
License-File: LICENSE
Requires-Dist: numpy
Requires-Dist: zarr
Requires-Dist: fsspec
Requires-Dist: deprecation
Requires-Dist: numcodecs
Requires-Dist: GitPython
